ocp_pipeline/__init__.py
ocp_pipeline/legacy.py
ocp_pipeline/opm.py
ocp_pipeline/version.py
ocp_pipeline/locale/ca-es/ADKeyword.voc
ocp_pipeline/locale/ca-es/ASMRKeyword.voc
ocp_pipeline/locale/ca-es/AdultKeyword.voc
ocp_pipeline/locale/ca-es/Alerts.voc
ocp_pipeline/locale/ca-es/AnimeKeyword.voc
ocp_pipeline/locale/ca-es/AudioBookKeyword.voc
ocp_pipeline/locale/ca-es/AudioDramaKeyword.voc
ocp_pipeline/locale/ca-es/AudioKeyword.voc
ocp_pipeline/locale/ca-es/BWKeyword.voc
ocp_pipeline/locale/ca-es/CartoonKeyword.voc
ocp_pipeline/locale/ca-es/ComicBookKeyword.voc
ocp_pipeline/locale/ca-es/DocumentaryKeyword.voc
ocp_pipeline/locale/ca-es/GameKeyword.voc
ocp_pipeline/locale/ca-es/HentaiKeyword.voc
ocp_pipeline/locale/ca-es/MovieKeyword.voc
ocp_pipeline/locale/ca-es/MusicKeyword.voc
ocp_pipeline/locale/ca-es/NewsKeyword.voc
ocp_pipeline/locale/ca-es/Parrot.voc
ocp_pipeline/locale/ca-es/Play.voc
ocp_pipeline/locale/ca-es/PodcastKeyword.voc
ocp_pipeline/locale/ca-es/RadioKeyword.voc
ocp_pipeline/locale/ca-es/Resume.voc
ocp_pipeline/locale/ca-es/SeriesKeyword.voc
ocp_pipeline/locale/ca-es/ShortKeyword.voc
ocp_pipeline/locale/ca-es/SilentKeyword.voc
ocp_pipeline/locale/ca-es/SoundIntents.voc
ocp_pipeline/locale/ca-es/TVKeyword.voc
ocp_pipeline/locale/ca-es/TrailerKeyword.voc
ocp_pipeline/locale/ca-es/VideoKeyword.voc
ocp_pipeline/locale/ca-es/audio_only.voc
ocp_pipeline/locale/ca-es/cant.play.dialog
ocp_pipeline/locale/ca-es/featured.intent
ocp_pipeline/locale/ca-es/just.one.moment.dialog
ocp_pipeline/locale/ca-es/like_song.intent
ocp_pipeline/locale/ca-es/load_game.intent
ocp_pipeline/locale/ca-es/media_stop.intent
ocp_pipeline/locale/ca-es/next.intent
ocp_pipeline/locale/ca-es/no.media.skills.dialog
ocp_pipeline/locale/ca-es/open.intent
ocp_pipeline/locale/ca-es/pause.intent
ocp_pipeline/locale/ca-es/play.intent
ocp_pipeline/locale/ca-es/play.what.dialog
ocp_pipeline/locale/ca-es/play_favorites.intent
ocp_pipeline/locale/ca-es/prev.intent
ovos_ocp_pipeline_plugin-1.1.18.dist-info/METADATA
ovos_ocp_pipeline_plugin-1.1.18.dist-info/WHEEL
ovos_ocp_pipeline_plugin-1.1.18.dist-info/entry_points.txt
ovos_ocp_pipeline_plugin-1.1.18.dist-info/top_level.txt
ovos_ocp_pipeline_plugin-1.1.18.dist-info/RECORD
