Metadata-Version: 2.4
Name: ovos_ocp_pipeline_plugin
Version: 1.1.18
Summary: media intent parser for OVOS
Home-page: https://github.com/OpenVoiceOS/ovos-ocp-pipeline-plugin
Author: JarbasAI
License: Apache License 2.0
Keywords: natural language processing
Classifier: Development Status :: 5 - Production/Stable
Classifier: Intended Audience :: Developers
Classifier: Topic :: Text Processing :: Linguistic
Classifier: License :: OSI Approved :: Apache Software License
Classifier: Programming Language :: Python :: 2.7
Classifier: Programming Language :: Python :: 3.5
Classifier: Programming Language :: Python :: 3.6
Classifier: Programming Language :: Python :: 3.7
Classifier: Programming Language :: Python :: 3.8
Classifier: Programming Language :: Python :: 3.9
Requires-Dist: ovos-workshop<8.0.0,>=0.1.7
Requires-Dist: ovos-utils<1.0.0,>=0.3.5
Requires-Dist: ovos-plugin-manager<3.0.0,>=1.0.0
Requires-Dist: ahocorasick-ner<1.0.0,>=0.1.1
Requires-Dist: langcodes
Dynamic: author
Dynamic: classifier
Dynamic: description-content-type
Dynamic: home-page
Dynamic: keywords
Dynamic: license
Dynamic: requires-dist
Dynamic: summary
